easy_sql/__init__.py
easy_sql/base_test.py
easy_sql/cli/__init__.py
easy_sql/cli/backend_processor.py
easy_sql/config/sql_config.py
easy_sql/config/sql_config_test.py
easy_sql/data_process.py
easy_sql/data_process_itest.py
easy_sql/data_process_test.py
easy_sql/local_spark.py
easy_sql/logger.py
easy_sql/report.py
easy_sql/report_test.py
easy_sql/spark_optimizer.py
easy_sql/sql_linter/__init__.py
easy_sql/sql_linter/rules/__init__.py
easy_sql/sql_linter/rules/bq_schema_rule.py
easy_sql/sql_linter/sql_linter.py
easy_sql/sql_linter/sql_linter_cli.py
easy_sql/sql_linter/sql_linter_reportor.py
easy_sql/sql_linter/sql_linter_test.py
easy_sql/sql_processor/__init__.py
easy_sql/sql_processor/backend/__init__.py
easy_sql/sql_processor/backend/base.py
easy_sql/sql_processor/backend/bigquery.py
easy_sql/sql_processor/backend/clickhouse.py
easy_sql/sql_processor/backend/flink.py
easy_sql/sql_processor/backend/flink_itest.py
easy_sql/sql_processor/backend/maxcompute.py
easy_sql/sql_processor/backend/maxcompute_itest.py
easy_sql/sql_processor/backend/postgres.py
easy_sql/sql_processor/backend/rdb.py
easy_sql/sql_processor/backend/rdb_itest.py
easy_sql/sql_processor/backend/rdb_test.py
easy_sql/sql_processor/backend/spark.py
easy_sql/sql_processor/backend/spark_test.py
easy_sql/sql_processor/backend/sql_dialect/__init__.py
easy_sql/sql_processor/backend/sql_dialect/bigquery.py
easy_sql/sql_processor/backend/sql_dialect/clickhouse.py
easy_sql/sql_processor/backend/sql_dialect/clickhouse_test.py
easy_sql/sql_processor/backend/sql_dialect/postgres.py
easy_sql/sql_processor/common.py
easy_sql/sql_processor/context.py
easy_sql/sql_processor/context_test.py
easy_sql/sql_processor/funcs.py
easy_sql/sql_processor/funcs_common.py
easy_sql/sql_processor/funcs_flink.py
easy_sql/sql_processor/funcs_flink_itest.py
easy_sql/sql_processor/funcs_itest.py
easy_sql/sql_processor/funcs_rdb.py
easy_sql/sql_processor/funcs_spark.py
easy_sql/sql_processor/report.py
easy_sql_easy_sql-1.1.0.dist-info/LICENSE
easy_sql_easy_sql-1.1.0.dist-info/METADATA
easy_sql_easy_sql-1.1.0.dist-info/WHEEL
easy_sql_easy_sql-1.1.0.dist-info/RECORD
