Metadata-Version: 2.1
Name: easy-sql-easy-sql
Version: 1.1.0
Summary: A library developed to ease the data ETL development process.
Home-page: https://easy-sql.readthedocs.io
License: Apache-2.0
Author: Easy SQL from Thoughtworks
Author-email: easy_sql@thoughtworks.com
Requires-Python: >=3.7,<4.0
Classifier: License :: OSI Approved :: Apache Software License
Classifier: Operating System :: MacOS
Classifier: Operating System :: POSIX :: Linux
Classifier: Programming Language :: Python :: 3
Classifier: Programming Language :: Python :: 3.7
Classifier: Programming Language :: Python :: 3.8
Classifier: Programming Language :: Python :: 3.9
Classifier: Programming Language :: Python :: 3.10
Classifier: Programming Language :: Python :: 3.11
Provides-Extra: cli
Provides-Extra: clickhouse
Provides-Extra: flink
Provides-Extra: linter
Provides-Extra: maxcompute
Provides-Extra: pg
Provides-Extra: spark
Provides-Extra: ydata-profiling
Requires-Dist: SQLAlchemy (>=1.4.40,<2.0.0) ; extra == "pg" or extra == "clickhouse"
Requires-Dist: apache-flink (>=1.17.0,<2.0.0) ; extra == "flink"
Requires-Dist: click (>=8.1.3,<9.0.0) ; extra == "cli"
Requires-Dist: clickhouse-driver (>=0.2.4,<0.3.0) ; extra == "clickhouse"
Requires-Dist: clickhouse-sqlalchemy (>=0.2.1,<0.3.0) ; extra == "clickhouse"
Requires-Dist: colorlog (>=6.6.0,<7.0.0) ; extra == "linter"
Requires-Dist: numpy (>=1.21.4,<1.22.0) ; python_version >= "3.7" and python_version < "3.11"
Requires-Dist: pandas (>=1.3,<1.4) ; python_full_version >= "3.7.1"
Requires-Dist: psycopg2 (>=2.9.3,<3.0.0) ; extra == "pg"
Requires-Dist: pymongo (>=3.8.0,<4.0.0)
Requires-Dist: pyodps (>=0.11.2.1,<0.12.0.0) ; extra == "maxcompute"
Requires-Dist: pyspark (>=2.3.0,!=3.1.1,!=3.1.2,!=3.1.3,!=3.2.0,!=3.2.1) ; extra == "spark"
Requires-Dist: pyyaml (>=6.0,<7.0) ; extra == "flink"
Requires-Dist: regex (>=2022.7.25,<2023.0.0) ; extra == "linter"
Requires-Dist: sqlfluff (>=1.4.5,<1.5.0) ; extra == "linter"
Requires-Dist: ydata-profiling (>=4.2.0,<5.0.0) ; (python_version >= "3.8" and python_version < "3.12") and (extra == "ydata-profiling")
Project-URL: Bug Tracker, https://github.com/easysql/easy_sql/issues
Project-URL: Repository, https://github.com/easysql/easy_sql
